pyproject.toml
tibanna_4dn/__init__.py
tibanna_4dn/__main__.py
tibanna_4dn/core.py
tibanna_4dn/iam_utils.py
tibanna_4dn/lambdas/__init__.py
tibanna_4dn/lambdas/check_task.py
tibanna_4dn/lambdas/requirements.txt
tibanna_4dn/lambdas/run_task.py
tibanna_4dn/lambdas/start_run.py
tibanna_4dn/lambdas/update_cost.py
tibanna_4dn/lambdas/update_ffmeta.py
tibanna_4dn/pony_utils.py
tibanna_4dn/start_run.py
tibanna_4dn/stepfunction.py
tibanna_4dn/stepfunction_cost_updater.py
tibanna_4dn/update_ffmeta.py
tibanna_4dn/vars.py
tibanna_cgap/__init__.py
tibanna_cgap/__main__.py
tibanna_cgap/check_task.py
tibanna_cgap/core.py
tibanna_cgap/cw_utils.py
tibanna_cgap/iam_utils.py
tibanna_cgap/lambdas/__init__.py
tibanna_cgap/lambdas/check_task.py
tibanna_cgap/lambdas/requirements.txt
tibanna_cgap/lambdas/run_task.py
tibanna_cgap/lambdas/start_run.py
tibanna_cgap/lambdas/update_cost.py
tibanna_cgap/lambdas/update_ffmeta.py
tibanna_cgap/start_run.py
tibanna_cgap/stepfunction.py
tibanna_cgap/stepfunction_cost_updater.py
tibanna_cgap/update_ffmeta.py
tibanna_cgap/vars.py
tibanna_cgap/zebra_utils.py
tibanna_ffcommon/__init__.py
tibanna_ffcommon/_version.py
tibanna_ffcommon/config.py
tibanna_ffcommon/core.py
tibanna_ffcommon/exceptions.py
tibanna_ffcommon/extra_files.py
tibanna_ffcommon/file_format.py
tibanna_ffcommon/generic_qc_utils.py
tibanna_ffcommon/iam_utils.py
tibanna_ffcommon/input_files.py
tibanna_ffcommon/misc_utils.py
tibanna_ffcommon/portal_utils.py
tibanna_ffcommon/qc.py
tibanna_ffcommon/stepfunction.py
tibanna_ffcommon/vars.py
tibanna_ffcommon/wfr.py
tibanna_smaht/__init__.py
tibanna_smaht/__main__.py
tibanna_smaht/check_task.py
tibanna_smaht/core.py
tibanna_smaht/cw_utils.py
tibanna_smaht/iam_utils.py
tibanna_smaht/lambdas/__init__.py
tibanna_smaht/lambdas/check_task.py
tibanna_smaht/lambdas/requirements.txt
tibanna_smaht/lambdas/run_task.py
tibanna_smaht/lambdas/start_run.py
tibanna_smaht/lambdas/update_cost.py
tibanna_smaht/lambdas/update_ffmeta.py
tibanna_smaht/start_run.py
tibanna_ff-3.7.0.dist-info/LICENSE.txt
tibanna_ff-3.7.0.dist-info/METADATA
tibanna_ff-3.7.0.dist-info/WHEEL
tibanna_ff-3.7.0.dist-info/entry_points.txt
tibanna_ff-3.7.0.dist-info/RECORD
