Metadata-Version: 2.1
Name: tibanna-ff
Version: 3.7.0
Summary: Tibanna runs portable pipelines (in CWL/WDL) on the AWS Cloud.
Home-page: http://github.com/4dn-dcic/tibanna_ff
License: MIT
Keywords: tibanna
Author: 4DN-DCIC Team
Author-email: support@4dnucleome.org
Requires-Python: >=3.8.1,<3.13
Classifier: License :: OSI Approved :: MIT License
Classifier: Natural Language :: English
Classifier: Operating System :: POSIX :: Linux
Classifier: Programming Language :: Python :: 3
Classifier: Programming Language :: Python :: 3.9
Classifier: Programming Language :: Python :: 3.10
Classifier: Programming Language :: Python :: 3.11
Classifier: Programming Language :: Python :: 3
Classifier: Programming Language :: Python :: 3.10
Classifier: Programming Language :: Python :: 3.11
Classifier: Programming Language :: Python :: 3.12
Classifier: Programming Language :: Python :: 3.8
Classifier: Programming Language :: Python :: 3.9
Requires-Dist: boto3 (>=1.34.147,<2.0.0)
Requires-Dist: botocore (>=1.34.147,<2.0.0)
Requires-Dist: dcicutils (>=8.13.3,<9.0.0)
Requires-Dist: pydantic (>=2.4.2,<3.0.0)
Requires-Dist: requests (==2.27.1)
Requires-Dist: tibanna (>=5.4.3,<6.0.0)
Requires-Dist: tomlkit (>=0.11.0,<0.12.0)
Project-URL: Repository, http://github.com/4dn-dcic/tibanna_ff.git
